langmiddle/__init__.py
langmiddle/context.py
langmiddle/history.py
langmiddle/py.typed
langmiddle/memory/__init__.py
langmiddle/memory/facts_manager.py
langmiddle/memory/facts_models.py
langmiddle/memory/facts_prompts.py
langmiddle/storage/__init__.py
langmiddle/storage/base.py
langmiddle/storage/firebase_backend.py
langmiddle/storage/postgres_backend.py
langmiddle/storage/postgres_base.py
langmiddle/storage/sqlite_backend.py
langmiddle/storage/supabase_backend.py
langmiddle/storage/postgres/chat_facts.sql
langmiddle/storage/postgres/chat_history.sql
langmiddle/storage/supabase/chat_facts.sql
langmiddle/storage/supabase/chat_history.sql
langmiddle/storage/supabase/client.py
langmiddle/storage/supabase/fact_maintenance.sql
langmiddle/utils/__init__.py
langmiddle/utils/logging.py
langmiddle/utils/messages.py
langmiddle/utils/runtime.py
langmiddle-0.1.4.dist-info/licenses/LICENSE
langmiddle-0.1.4.dist-info/METADATA
langmiddle-0.1.4.dist-info/WHEEL
langmiddle-0.1.4.dist-info/top_level.txt
langmiddle-0.1.4.dist-info/RECORD
