Metadata-Version: 2.4
Name: langmiddle
Version: 0.1.4
Summary: Middlewares for LangChain / LangGraph
Author-email: Alpha x1 <alpha.xone@outlook.com>
License: MIT
Project-URL: Homepage, https://github.com/alpha-xone/langmiddle
Project-URL: Repository, https://github.com/alpha-xone/langmiddle
Project-URL: Issues, https://github.com/alpha-xone/langmiddle/issues
Project-URL: Documentation, https://github.com/alpha-xone/langmiddle#readme
Keywords: langchain,langgraph,middleware,ai,llm,agents
Classifier: Development Status :: 3 - Alpha
Classifier: Intended Audience :: Developers
Classifier: License :: OSI Approved :: MIT License
Classifier: Programming Language :: Python :: 3
Classifier: Programming Language :: Python :: 3.10
Classifier: Programming Language :: Python :: 3.11
Classifier: Programming Language :: Python :: 3.12
Classifier: Programming Language :: Python :: 3.13
Classifier: Topic :: Software Development :: Libraries :: Python Modules
Classifier: Topic :: Scientific/Engineering :: Artificial Intelligence
Classifier: Topic :: Software Development :: Libraries :: Application Frameworks
Requires-Python: >=3.10
License-File: LICENSE
Requires-Dist: langchain
Requires-Dist: langgraph
Requires-Dist: langchain-core
Provides-Extra: dev
Requires-Dist: pytest>=7.0; extra == "dev"
Requires-Dist: black>=22.0; extra == "dev"
Requires-Dist: isort>=5.0; extra == "dev"
Requires-Dist: flake8>=4.0; extra == "dev"
Requires-Dist: mypy>=0.950; extra == "dev"
Requires-Dist: build>=0.8; extra == "dev"
Requires-Dist: twine>=4.0; extra == "dev"
Provides-Extra: postgres
Requires-Dist: psycopg2-binary>=2.9.0; extra == "postgres"
Requires-Dist: python-dotenv>=1.0.0; extra == "postgres"
Provides-Extra: supabase
Requires-Dist: supabase>=2.20.0; extra == "supabase"
Requires-Dist: python-jose>=3.3.0; extra == "supabase"
Requires-Dist: python-dotenv>=1.0.0; extra == "supabase"
Requires-Dist: psycopg2-binary>=2.9.0; extra == "supabase"
Provides-Extra: firebase
Requires-Dist: firebase-admin>=6.0.0; extra == "firebase"
Provides-Extra: all
Requires-Dist: supabase>=2.20.0; extra == "all"
Requires-Dist: python-jose>=3.3.0; extra == "all"
Requires-Dist: python-dotenv>=1.0.0; extra == "all"
Requires-Dist: psycopg2-binary>=2.9.0; extra == "all"
Requires-Dist: firebase-admin>=6.0.0; extra == "all"
Dynamic: license-file
